Metadata-Version: 2.1
Name: modulepy
Version: 0.17
Summary: module framework
Home-page: https://github.com/nbdy/modulepy
Author: Pascal Eberlein
Author-email: pascal@eberlein.io
License: UNKNOWN
Keywords: modularity modules
Platform: UNKNOWN
Classifier: Intended Audience :: Developers
Classifier: Topic :: Software Development :: Build Tools
Classifier: License :: OSI Approved :: MIT License
Classifier: Programming Language :: Python :: 3
License-File: LICENSE
